{
  "schemaVersion": 1,
  "featureId": "feat_library_be60d35594",
  "title": "Node source packages/server/src/models",
  "summary": "Node/TypeScript source group packages/server/src/models with 8 files.",
  "kind": "library",
  "source": "node-source-group",
  "confidence": "medium",
  "entrypoints": [
    {
      "path": "packages/server/package.json",
      "symbol": "packages/server/src/models",
      "route": null,
      "command": null
    }
  ],
  "ownedFiles": [
    {
      "path": "packages/server/src/models/ActivityRoom.js",
      "reason": "source group packages/server/src/models"
    },
    {
      "path": "packages/server/src/models/HandoutRoom.js",
      "reason": "source group packages/server/src/models"
    },
    {
      "path": "packages/server/src/models/LinkShareRoom.js",
      "reason": "source group packages/server/src/models"
    },
    {
      "path": "packages/server/src/models/PollRoom.js",
      "reason": "source group packages/server/src/models"
    },
    {
      "path": "packages/server/src/models/QuestionsRoom.js",
      "reason": "source group packages/server/src/models"
    },
    {
      "path": "packages/server/src/models/RTFeedbackRoom.js",
      "reason": "source group packages/server/src/models"
    },
    {
      "path": "packages/server/src/models/Room.js",
      "reason": "source group packages/server/src/models"
    },
    {
      "path": "packages/server/src/models/Session.js",
      "reason": "source group packages/server/src/models"
    }
  ],
  "contextFiles": [
    {
      "path": "packages/server/package.json",
      "reason": "package manifest"
    },
    {
      "path": "packages/server/src/models/ActivityRoom.test.js",
      "reason": "associated test"
    }
  ],
  "tests": [
    {
      "path": "packages/server/src/models/ActivityRoom.test.js",
      "command": "npm --prefix packages/server run test"
    }
  ],
  "tags": [
    "node",
    "typescript",
    "source-group",
    "project:@classroom-widgets/server",
    "project-root:packages/server"
  ],
  "trustBoundaries": [],
  "status": "pending",
  "lock": null,
  "findingIds": [],
  "patchAttemptIds": [],
  "analysisHistory": [],
  "createdAt": "2026-05-18T12:09:19.825Z",
  "updatedAt": "2026-05-18T12:09:19.825Z"
}
