{
  "schemaVersion": 1,
  "runId": "20260518T121639-0656ac",
  "command": "revalidate",
  "args": [
    "revalidate",
    "--finding",
    "fnd_sig-feat-config-7528cb5b98-efa77_b84fde3e51",
    "--json"
  ],
  "rootPath": "C:/Users/yjsoon/Developer/classroom-widgets",
  "headSha": "71fd11988e5a0879c11c4acd5e786d5f8211544a",
  "startedAt": "2026-05-18T12:16:39.437Z",
  "finishedAt": "2026-05-18T12:18:48.246Z",
  "status": "completed",
  "claimedFeatureIds": [],
  "findingIds": [
    "fnd_sig-feat-config-7528cb5b98-efa77_b84fde3e51"
  ],
  "patchAttemptIds": [],
  "errors": []
}
